Workbook
Name Slicer_Branch: #N/A
Name Slicer_City: #N/A
Name Slicer_Month: #N/A
Name Slicer_Product_line: #N/A

Sheet Raw_Data
A1: Invoice ID | B1: Branch | C1: City | D1: Customer type | E1: Gender | F1: Product line | G1: Unit price | H1: Quantity | I1: Tax 5% | J1: Sales | K1: Date | L1: Time | M1: Payment | N1: cogs | O1: gross margin percentage | P1: gross income | Q1: Rating | R1: Column1 | S1: _1 | T1: _2 | U1: _3
A2: 750-67-8428 | B2: Alex | C2: Yangon | D2: Member | E2: Female | F2: Health and beauty | G2: 74.69 | H2: 7 | I2: 26.1415 | J2: 548.9715 | K2: 1/5/2019 | L2: 1:08:00 PM | M2: Ewallet | N2: 522.83 | O2: 4.761904762 | P2: 26.1415 | Q2: 9.1
A3: 226-31-3081 | B3: Giza | C3: Naypyitaw | D3: Normal | E3: Female | F3: Electronic accessories | G3: 15.28 | H3: 5 | I3: 3.82 | J3: 80.22 | K3: 3/8/2019 | L3: 10:29:00 AM | M3: Cash | N3: 76.4 | O3: 4.761904762 | P3: 3.82 | Q3: 9.6
A4: 631-41-3108 | B4: Alex | C4: Yangon | D4: Normal | E4: Female | F4: Home and lifestyle | G4: 46.33 | H4: 7 | I4: 16.2155 | J4: 340.5255 | K4: 3/3/2019 | L4: 1:23:00 PM | M4: Credit card | N4: 324.31 | O4: 4.761904762 | P4: 16.2155 | Q4: 7.4
A5: 123-19-1176 | B5: Alex | C5: Yangon | D5: Member | E5: Female | F5: Health and beauty | G5: 58.22 | H5: 8 | I5: 23.288 | J5: 489.048 | K5: 1/27/2019 | L5: 8:33:00 PM | M5: Ewallet | N5: 465.76 | O5: 4.761904762 | P5: 23.288 | Q5: 8.4
A6: 373-73-7910 | B6: Alex | C6: Yangon | D6: Member | E6: Female | F6: Sports and travel | G6: 86.31 | H6: 7 | I6: 30.2085 | J6: 634.3785 | K6: 2/8/2019 | L6: 10:37:00 AM | M6: Ewallet | N6: 604.17 | O6: 4.761904762 | P6: 30.2085 | Q6: 5.3
A7: 699-14-3026 | B7: Giza | C7: Naypyitaw | D7: Member | E7: Female | F7: Electronic accessories | G7: 85.39 | H7: 7 | I7: 29.8865 | J7: 627.6165 | K7: 3/25/2019 | L7: 6:30:00 PM | M7: Ewallet | N7: 597.73 | O7: 4.761904762 | P7: 29.8865 | Q7: 4.1
A8: 355-53-5943 | B8: Alex | C8: Yangon | D8: Member | E8: Female | F8: Electronic accessories | G8: 68.84 | H8: 6 | I8: 20.652 | J8: 433.692 | K8: 2/25/2019 | L8: 2:36:00 PM | M8: Ewallet | N8: 413.04 | O8: 4.761904762 | P8: 20.652 | Q8: 5.8
A9: 315-22-5665 | B9: Giza | C9: Naypyitaw | D9: Member | E9: Female | F9: Home and lifestyle | G9: 73.56 | H9: 10 | I9: 36.78 | J9: 772.38 | K9: 2/24/2019 | L9: 11:38:00 AM | M9: Ewallet | N9: 735.6 | O9: 4.761904762 | P9: 36.78 | Q9: 8
A10: 665-32-9167 | B10: Alex | C10: Yangon | D10: Member | E10: Female | F10: Health and beauty | G10: 36.26 | H10: 2 | I10: 3.626 | J10: 76.146 | K10: 1/10/2019 | L10: 5:15:00 PM | M10: Credit card | N10: 72.52 | O10: 4.761904762 | P10: 3.626 | Q10: 7.2
A11: 692-92-5582 | B11: Cairo | C11: Mandalay | D11: Member | E11: Female | F11: Food and beverages | G11: 54.84 | H11: 3 | I11: 8.226 | J11: 172.746 | K11: 2/20/2019 | L11: 1:27:00 PM | M11: Credit card | N11: 164.52 | O11: 4.761904762 | P11: 8.226 | Q11: 5.9
A12: 351-62-0822 | B12: Cairo | C12: Mandalay | D12: Member | E12: Female | F12: Fashion accessories | G12: 14.48 | H12: 4 | I12: 2.896 | J12: 60.816 | K12: 2/6/2019 | L12: 6:07:00 PM | M12: Ewallet | N12: 57.92 | O12: 4.761904762 | P12: 2.896 | Q12: 4.5
A13: 529-56-3974 | B13: Cairo | C13: Mandalay | D13: Member | E13: Female | F13: Electronic accessories | G13: 25.51 | H13: 4 | I13: 5.102 | J13: 107.142 | K13: 3/9/2019 | L13: 5:03:00 PM | M13: Cash | N13: 102.04 | O13: 4.761904762 | P13: 5.102 | Q13: 6.8
... A1001: 849-09-3807 | B1001: Alex | C1001: Yangon | D1001: Member | E1001: Female | F1001: Fashion accessories | G1001: 88.34 | H1001: 7 | I1001: 30.919 | J1001: 649.299 | K1001: 2/18/2019 | L1001: 1:28:00 PM | M1001: Cash | N1001: 618.38 | O1001: 4.761904762 | P1001: 30.919 | Q1001: 6.6

Sheet Data_Cleaning
A1: Invoice_ID | B1: Branch | C1: City | D1: Customer type | E1: Gender | F1: Product line | G1: Unit price | H1: Quantity | I1: Tax 5% | J1: Sales | K1: Date | L1: Time | M1: Payment | N1: cogs | O1: gross margin percentage | P1: gross income | Q1: Rating | R1: Column1 | S1: Column2 | T1: Column3 | U1: _1 | V1: _2 | W1: _3
A2: 750-67-8428 | B2: Alex | C2: Yangon | D2: Member | E2: Female | F2: Health and beauty | G2: 74.69 | H2: 7 | I2: 26.1415 | J2: 548.9715 | K2: 43470 | L2: 0.54722222 | M2: Ewallet | N2: 522.83 | O2: 4.7619048 | P2: 26.1415 | Q2: 9.1
A3: 226-31-3081 | B3: Giza | C3: Naypyitaw | D3: Normal | E3: Female | F3: Electronic accessories | G3: 15.28 | H3: 5 | I3: 3.82 | J3: 80.22 | K3: 43532 | L3: 0.43680556 | M3: Cash | N3: 76.4 | O3: 4.7619048 | P3: 3.82 | Q3: 9.6
A4: 631-41-3108 | B4: Alex | C4: Yangon | D4: Normal | E4: Female | F4: Home and lifestyle | G4: 46.33 | H4: 7 | I4: 16.2155 | J4: 340.5255 | K4: 43527 | L4: 0.55763889 | M4: Credit card | N4: 324.31 | O4: 4.7619048 | P4: 16.2155 | Q4: 7.4
A5: 123-19-1176 | B5: Alex | C5: Yangon | D5: Member | E5: Female | F5: Health and beauty | G5: 58.22 | H5: 8 | I5: 23.288 | J5: 489.048 | K5: 43492 | L5: 0.85625 | M5: Ewallet | N5: 465.76 | O5: 4.7619048 | P5: 23.288 | Q5: 8.4
A6: 373-73-7910 | B6: Alex | C6: Yangon | D6: Member | E6: Female | F6: Sports and travel | G6: 86.31 | H6: 7 | I6: 30.2085 | J6: 634.3785 | K6: 43504 | L6: 0.44236111 | M6: Ewallet | N6: 604.17 | O6: 4.7619048 | P6: 30.2085 | Q6: 5.3
A7: 699-14-3026 | B7: Giza | C7: Naypyitaw | D7: Member | E7: Female | F7: Electronic accessories | G7: 85.39 | H7: 7 | I7: 29.8865 | J7: 627.6165 | K7: 43549 | L7: 0.77083333 | M7: Ewallet | N7: 597.73 | O7: 4.7619048 | P7: 29.8865 | Q7: 4.1
A8: 355-53-5943 | B8: Alex | C8: Yangon | D8: Member | E8: Female | F8: Electronic accessories | G8: 68.84 | H8: 6 | I8: 20.652 | J8: 433.692 | K8: 43521 | L8: 0.60833333 | M8: Ewallet | N8: 413.04 | O8: 4.7619048 | P8: 20.652 | Q8: 5.8
A9: 315-22-5665 | B9: Giza | C9: Naypyitaw | D9: Member | E9: Female | F9: Home and lifestyle | G9: 73.56 | H9: 10 | I9: 36.78 | J9: 772.38 | K9: 43520 | L9: 0.48472222 | M9: Ewallet | N9: 735.6 | O9: 4.7619048 | P9: 36.78 | Q9: 8
A10: 665-32-9167 | B10: Alex | C10: Yangon | D10: Member | E10: Female | F10: Health and beauty | G10: 36.26 | H10: 2 | I10: 3.626 | J10: 76.146 | K10: 43475 | L10: 0.71875 | M10: Credit card | N10: 72.52 | O10: 4.7619048 | P10: 3.626 | Q10: 7.2
A11: 692-92-5582 | B11: Cairo | C11: Mandalay | D11: Member | E11: Female | F11: Food and beverages | G11: 54.84 | H11: 3 | I11: 8.226 | J11: 172.746 | K11: 43516 | L11: 0.56041667 | M11: Credit card | N11: 164.52 | O11: 4.7619048 | P11: 8.226 | Q11: 5.9
A12: 351-62-0822 | B12: Cairo | C12: Mandalay | D12: Member | E12: Female | F12: Fashion accessories | G12: 14.48 | H12: 4 | I12: 2.896 | J12: 60.816 | K12: 43502 | L12: 0.75486111 | M12: Ewallet | N12: 57.92 | O12: 4.7619048 | P12: 2.896 | Q12: 4.5
A13: 529-56-3974 | B13: Cairo | C13: Mandalay | D13: Member | E13: Female | F13: Electronic accessories | G13: 25.51 | H13: 4 | I13: 5.102 | J13: 107.142 | K13: 43533 | L13: 0.71041667 | M13: Cash | N13: 102.04 | O13: 4.7619048 | P13: 5.102 | Q13: 6.8
... A1001: 849-09-3807 | B1001: Alex | C1001: Yangon | D1001: Member | E1001: Female | F1001: Fashion accessories | G1001: 88.34 | H1001: 7 | I1001: 30.919 | J1001: 649.299 | K1001: 43514 | L1001: 0.56111111 | M1001: Cash | N1001: 618.38 | O1001: 4.7619048 | P1001: 30.919 | Q1001: 6.6

Sheet Analysis
A1: Invoice_ID | B1: Branch | C1: City | D1: Customer type | E1: Gender | F1: Product line | G1: Unit price | H1: Quantity | I1: Tax 5% | J1: Sales | K1: Date | L1: Time | M1: Payment | N1: cogs | O1: gross margin percentage | P1: gross income | Q1: Rating | R1: Month | S1: Month Number | T1: Order Size | U1: Order Status | V1: Column1 | W1: Metric | X1: Value | Y1: _22 | Z1: _3
A2: 750-67-8428 | B2: Alex | C2: Yangon | D2: Member | E2: Female | F2: Health and beauty | G2: 74.69 | H2: 7 | I2: 26.1415 | J2: 548.9715 | K2: 43470 | L2: 0.54722222 | M2: Ewallet | N2: 522.83 | O2: 4.7619048 | P2: 26.1415 | Q2: 9.1 | R2: =TEXT(K2,"mmmm") -> January | S2: =MONTH(K2) -> 1 | T2: =IF(tbl_sales[[#This Row],[Sales]]>=500,"High Value","Standard") -> High Value | U2: =IF(tbl_sales[[#This Row],[Order Size]]="High Value","High Value Order","Standard Order") -> High Value Order | W2: Total Sales | X2: =SUM(J2:J1001) -> 322966.75
A3: 226-31-3081 | B3: Giza | C3: Naypyitaw | D3: Normal | E3: Female | F3: Electronic accessories | G3: 15.28 | H3: 5 | I3: 3.82 | J3: 80.22 | K3: 43532 | L3: 0.43680556 | M3: Cash | N3: 76.4 | O3: 4.7619048 | P3: 3.82 | Q3: 9.6 | R3: =TEXT(K3,"mmmm") -> March | S3: =MONTH(K3) -> 3 | T3: =IF(tbl_sales[[#This Row],[Sales]]>=500,"High Value","Standard") -> Standard | U3: =IF(tbl_sales[[#This Row],[Order Size]]="High Value","High Value Order","Standard Order") -> Standard Order | W3: Total Quantity | X3: =SUM(H2:H1001) -> 5510
A4: 631-41-3108 | B4: Alex | C4: Yangon | D4: Normal | E4: Female | F4: Home and lifestyle | G4: 46.33 | H4: 7 | I4: 16.2155 | J4: 340.5255 | K4: 43527 | L4: 0.55763889 | M4: Credit card | N4: 324.31 | O4: 4.7619048 | P4: 16.2155 | Q4: 7.4 | R4: =TEXT(K4,"mmmm") -> March | S4: =MONTH(K4) -> 3 | T4: =IF(tbl_sales[[#This Row],[Sales]]>=500,"High Value","Standard") -> Standard | U4: =IF(tbl_sales[[#This Row],[Order Size]]="High Value","High Value Order","Standard Order") -> Standard Order | W4: Total COGS | X4: =SUM(N2:N1001) -> 307587.38
A5: 123-19-1176 | B5: Alex | C5: Yangon | D5: Member | E5: Female | F5: Health and beauty | G5: 58.22 | H5: 8 | I5: 23.288 | J5: 489.048 | K5: 43492 | L5: 0.85625 | M5: Ewallet | N5: 465.76 | O5: 4.7619048 | P5: 23.288 | Q5: 8.4 | R5: =TEXT(K5,"mmmm") -> January | S5: =MONTH(K5) -> 1 | T5: =IF(tbl_sales[[#This Row],[Sales]]>=500,"High Value","Standard") -> Standard | U5: =IF(tbl_sales[[#This Row],[Order Size]]="High Value","High Value Order","Standard Order") -> Standard Order | W5: Total Gross Income | X5: =SUM(P2:P1001) -> 15379.369
A6: 373-73-7910 | B6: Alex | C6: Yangon | D6: Member | E6: Female | F6: Sports and travel | G6: 86.31 | H6: 7 | I6: 30.2085 | J6: 634.3785 | K6: 43504 | L6: 0.44236111 | M6: Ewallet | N6: 604.17 | O6: 4.7619048 | P6: 30.2085 | Q6: 5.3 | R6: =TEXT(K6,"mmmm") -> February | S6: =MONTH(K6) -> 2 | T6: =IF(tbl_sales[[#This Row],[Sales]]>=500,"High Value","Standard") -> High Value | U6: =IF(tbl_sales[[#This Row],[Order Size]]="High Value","High Value Order","Standard Order") -> High Value Order | W6: Average Rating | X6: =AVERAGE(Q2:Q1001) -> 6.9727
A7: 699-14-3026 | B7: Giza | C7: Naypyitaw | D7: Member | E7: Female | F7: Electronic accessories | G7: 85.39 | H7: 7 | I7: 29.8865 | J7: 627.6165 | K7: 43549 | L7: 0.77083333 | M7: Ewallet | N7: 597.73 | O7: 4.7619048 | P7: 29.8865 | Q7: 4.1 | R7: =TEXT(K7,"mmmm") -> March | S7: =MONTH(K7) -> 3 | T7: =IF(tbl_sales[[#This Row],[Sales]]>=500,"High Value","Standard") -> High Value | U7: =IF(tbl_sales[[#This Row],[Order Size]]="High Value","High Value Order","Standard Order") -> High Value Order
A8: 355-53-5943 | B8: Alex | C8: Yangon | D8: Member | E8: Female | F8: Electronic accessories | G8: 68.84 | H8: 6 | I8: 20.652 | J8: 433.692 | K8: 43521 | L8: 0.60833333 | M8: Ewallet | N8: 413.04 | O8: 4.7619048 | P8: 20.652 | Q8: 5.8 | R8: =TEXT(K8,"mmmm") -> February | S8: =MONTH(K8) -> 2 | T8: =IF(tbl_sales[[#This Row],[Sales]]>=500,"High Value","Standard") -> Standard | U8: =IF(tbl_sales[[#This Row],[Order Size]]="High Value","High Value Order","Standard Order") -> Standard Order | W8: Branch | X8: Total Sales
A9: 315-22-5665 | B9: Giza | C9: Naypyitaw | D9: Member | E9: Female | F9: Home and lifestyle | G9: 73.56 | H9: 10 | I9: 36.78 | J9: 772.38 | K9: 43520 | L9: 0.48472222 | M9: Ewallet | N9: 735.6 | O9: 4.7619048 | P9: 36.78 | Q9: 8 | R9: =TEXT(K9,"mmmm") -> February | S9: =MONTH(K9) -> 2 | T9: =IF(tbl_sales[[#This Row],[Sales]]>=500,"High Value","Standard") -> High Value | U9: =IF(tbl_sales[[#This Row],[Order Size]]="High Value","High Value Order","Standard Order") -> High Value Order | W9: Alex | X9: =SUMIF(tbl_sales[Branch],"Alex",tbl_sales[Sales]) -> 106200.37
A10: 665-32-9167 | B10: Alex | C10: Yangon | D10: Member | E10: Female | F10: Health and beauty | G10: 36.26 | H10: 2 | I10: 3.626 | J10: 76.146 | K10: 43475 | L10: 0.71875 | M10: Credit card | N10: 72.52 | O10: 4.7619048 | P10: 3.626 | Q10: 7.2 | R10: =TEXT(K10,"mmmm") -> January | S10: =MONTH(K10) -> 1 | T10: =IF(tbl_sales[[#This Row],[Sales]]>=500,"High Value","Standard") -> Standard | U10: =IF(tbl_sales[[#This Row],[Order Size]]="High Value","High Value Order","Standard Order") -> Standard Order | W10: Cairo | X10: =SUMIF(tbl_sales[Branch],"Cairo",tbl_sales[Sales]) -> 106197.67
A11: 692-92-5582 | B11: Cairo | C11: Mandalay | D11: Member | E11: Female | F11: Food and beverages | G11: 54.84 | H11: 3 | I11: 8.226 | J11: 172.746 | K11: 43516 | L11: 0.56041667 | M11: Credit card | N11: 164.52 | O11: 4.7619048 | P11: 8.226 | Q11: 5.9 | R11: =TEXT(K11,"mmmm") -> February | S11: =MONTH(K11) -> 2 | T11: =IF(tbl_sales[[#This Row],[Sales]]>=500,"High Value","Standard") -> Standard | U11: =IF(tbl_sales[[#This Row],[Order Size]]="High Value","High Value Order","Standard Order") -> Standard Order | W11: Giza | X11: =SUMIF(tbl_sales[Branch],"Giza",tbl_sales[Sales]) -> 110568.71
A12: 351-62-0822 | B12: Cairo | C12: Mandalay | D12: Member | E12: Female | F12: Fashion accessories | G12: 14.48 | H12: 4 | I12: 2.896 | J12: 60.816 | K12: 43502 | L12: 0.75486111 | M12: Ewallet | N12: 57.92 | O12: 4.7619048 | P12: 2.896 | Q12: 4.5 | R12: =TEXT(K12,"mmmm") -> February | S12: =MONTH(K12) -> 2 | T12: =IF(tbl_sales[[#This Row],[Sales]]>=500,"High Value","Standard") -> Standard | U12: =IF(tbl_sales[[#This Row],[Order Size]]="High Value","High Value Order","Standard Order") -> Standard Order
A13: 529-56-3974 | B13: Cairo | C13: Mandalay | D13: Member | E13: Female | F13: Electronic accessories | G13: 25.51 | H13: 4 | I13: 5.102 | J13: 107.142 | K13: 43533 | L13: 0.71041667 | M13: Cash | N13: 102.04 | O13: 4.7619048 | P13: 5.102 | Q13: 6.8 | R13: =TEXT(K13,"mmmm") -> March | S13: =MONTH(K13) -> 3 | T13: =IF(tbl_sales[[#This Row],[Sales]]>=500,"High Value","Standard") -> Standard | U13: =IF(tbl_sales[[#This Row],[Order Size]]="High Value","High Value Order","Standard Order") -> Standard Order | W13: Month | X13: Total Sales
A14: 365-64-0515 | B14: Alex | C14: Yangon | D14: Member | E14: Female | F14: Electronic accessories | G14: 46.95 | H14: 5 | I14: 11.7375 | J14: 246.4875 | K14: 43508 | L14: 0.43402778 | M14: Ewallet | N14: 234.75 | O14: 4.7619048 | P14: 11.7375 | Q14: 7.1 | R14: =TEXT(K14,"mmmm") -> February | S14: =MONTH(K14) -> 2 | T14: =IF(tbl_sales[[#This Row],[Sales]]>=500,"High Value","Standard") -> Standard | U14: =IF(tbl_sales[[#This Row],[Order Size]]="High Value","High Value Order","Standard Order") -> Standard Order | W14: January | X14: =SUMIF(tbl_sales[Month],"January",tbl_sales[Sales]) -> 116291.87
A15: 252-56-2699 | B15: Alex | C15: Yangon | D15: Member | E15: Female | F15: Food and beverages | G15: 43.19 | H15: 10 | I15: 21.595 | J15: 453.495 | K15: 43503 | L15: 0.7 | M15: Ewallet | N15: 431.9 | O15: 4.7619048 | P15: 21.595 | Q15: 8.2 | R15: =TEXT(K15,"mmmm") -> February | S15: =MONTH(K15) -> 2 | T15: =IF(tbl_sales[[#This Row],[Sales]]>=500,"High Value","Standard") -> Standard | U15: =IF(tbl_sales[[#This Row],[Order Size]]="High Value","High Value Order","Standard Order") -> Standard Order | W15: February | X15: =SUMIF(tbl_sales[Month],"February",tbl_sales[Sales]) -> 97219.374
A16: 829-34-3910 | B16: Alex | C16: Yangon | D16: Member | E16: Female | F16: Health and beauty | G16: 71.38 | H16: 10 | I16: 35.69 | J16: 749.49 | K16: 43553 | L16: 0.80625 | M16: Cash | N16: 713.8 | O16: 4.7619048 | P16: 35.69 | Q16: 5.7 | R16: =TEXT(K16,"mmmm") -> March | S16: =MONTH(K16) -> 3 | T16: =IF(tbl_sales[[#This Row],[Sales]]>=500,"High Value","Standard") -> High Value | U16: =IF(tbl_sales[[#This Row],[Order Size]]="High Value","High Value Order","Standard Order") -> High Value Order | W16: March | X16: =SUMIF(tbl_sales[Month],"March",tbl_sales[Sales]) -> 109455.51
A17: 299-46-1805 | B17: Cairo | C17: Mandalay | D17: Member | E17: Female | F17: Sports and travel | G17: 93.72 | H17: 6 | I17: 28.116 | J17: 590.436 | K17: 43480 | L17: 0.67986111 | M17: Cash | N17: 562.32 | O17: 4.7619048 | P17: 28.116 | Q17: 4.5 | R17: =TEXT(K17,"mmmm") -> January | S17: =MONTH(K17) -> 1 | T17: =IF(tbl_sales[[#This Row],[Sales]]>=500,"High Value","Standard") -> High Value | U17: =IF(tbl_sales[[#This Row],[Order Size]]="High Value","High Value Order","Standard Order") -> High Value Order
A18: 656-95-9349 | B18: Alex | C18: Yangon | D18: Member | E18: Female | F18: Health and beauty | G18: 68.93 | H18: 7 | I18: 24.1255 | J18: 506.6355 | K18: 43535 | L18: 0.46041667 | M18: Credit card | N18: 482.51 | O18: 4.7619048 | P18: 24.1255 | Q18: 4.6 | R18: =TEXT(K18,"mmmm") -> March | S18: =MONTH(K18) -> 3 | T18: =IF(tbl_sales[[#This Row],[Sales]]>=500,"High Value","Standard") -> High Value | U18: =IF(tbl_sales[[#This Row],[Order Size]]="High Value","High Value Order","Standard Order") -> High Value Order | W18: Order Size | X18: Number of Orders
A19: 765-26-6951 | B19: Alex | C19: Yangon | D19: Member | E19: Female | F19: Sports and travel | G19: 72.61 | H19: 6 | I19: 21.783 | J19: 457.443 | K19: 43466 | L19: 0.44375 | M19: Credit card | N19: 435.66 | O19: 4.7619048 | P19: 21.783 | Q19: 6.9 | R19: =TEXT(K19,"mmmm") -> January | S19: =MONTH(K19) -> 1 | T19: =IF(tbl_sales[[#This Row],[Sales]]>=500,"High Value","Standard") -> Standard | U19: =IF(tbl_sales[[#This Row],[Order Size]]="High Value","High Value Order","Standard Order") -> Standard Order | W19: Standard | X19: =COUNTIF(tbl_sales[Order Size],"Standard") -> 774
A20: 329-62-1586 | B20: Alex | C20: Yangon | D20: Member | E20: Female | F20: Food and beverages | G20: 54.67 | H20: 3 | I20: 8.2005 | J20: 172.2105 | K20: 43486 | L20: 0.75 | M20: Credit card | N20: 164.01 | O20: 4.7619048 | P20: 8.2005 | Q20: 8.6 | R20: =TEXT(K20,"mmmm") -> January | S20: =MONTH(K20) -> 1 | T20: =IF(tbl_sales[[#This Row],[Sales]]>=500,"High Value","Standard") -> Standard | U20: =IF(tbl_sales[[#This Row],[Order Size]]="High Value","High Value Order","Standard Order") -> Standard Order | W20: High Value | X20: =COUNTIF(tbl_sales[Order Size],"High Value") -> 227
A21: 319-50-3348 | B21: Cairo | C21: Mandalay | D21: Member | E21: Female | F21: Home and lifestyle | G21: 40.3 | H21: 2 | I21: 4.03 | J21: 84.63 | K21: 43535 | L21: 0.64583333 | M21: Ewallet | N21: 80.6 | O21: 4.7619048 | P21: 4.03 | Q21: 4.4 | R21: =TEXT(K21,"mmmm") -> March | S21: =MONTH(K21) -> 3 | T21: =IF(tbl_sales[[#This Row],[Sales]]>=500,"High Value","Standard") -> Standard | U21: =IF(tbl_sales[[#This Row],[Order Size]]="High Value","High Value Order","Standard Order") -> Standard Order
A22: 300-71-4605 | B22: Giza | C22: Naypyitaw | D22: Member | E22: Female | F22: Electronic accessories | G22: 86.04 | H22: 5 | I22: 21.51 | J22: 451.71 | K22: 43521 | L22: 0.475 | M22: Ewallet | N22: 430.2 | O22: 4.7619048 | P22: 21.51 | Q22: 4.8 | R22: =TEXT(K22,"mmmm") -> February | S22: =MONTH(K22) -> 2 | T22: =IF(tbl_sales[[#This Row],[Sales]]>=500,"High Value","Standard") -> Standard | U22: =IF(tbl_sales[[#This Row],[Order Size]]="High Value","High Value Order","Standard Order") -> Standard Order | W22: Product Line | X22: Total Sales
A23: 371-85-5789 | B23: Cairo | C23: Mandalay | D23: Member | E23: Female | F23: Health and beauty | G23: 87.98 | H23: 3 | I23: 13.197 | J23: 277.137 | K23: 43529 | L23: 0.44444444 | M23: Ewallet | N23: 263.94 | O23: 4.7619048 | P23: 13.197 | Q23: 5.1 | R23: =TEXT(K23,"mmmm") -> March | S23: =MONTH(K23) -> 3 | T23: =IF(tbl_sales[[#This Row],[Sales]]>=500,"High Value","Standard") -> Standard | U23: =IF(tbl_sales[[#This Row],[Order Size]]="High Value","High Value Order","Standard Order") -> Standard Order | W23: Electronic accessories | X23: =SUMIF(tbl_sales[Product line],"Electronic accessories",tbl_sales[Sales]) -> 54337.532
A24: 273-16-6619 | B24: Cairo | C24: Mandalay | D24: Member | E24: Female | F24: Home and lifestyle | G24: 33.2 | H24: 2 | I24: 3.32 | J24: 69.72 | K24: 43539 | L24: 0.51388889 | M24: Credit card | N24: 66.4 | O24: 4.7619048 | P24: 3.32 | Q24: 4.4 | R24: =TEXT(K24,"mmmm") -> March | S24: =MONTH(K24) -> 3 | T24: =IF(tbl_sales[[#This Row],[Sales]]>=500,"High Value","Standard") -> Standard | U24: =IF(tbl_sales[[#This Row],[Order Size]]="High Value","High Value Order","Standard Order") -> Standard Order | W24: Home and lifestyle | X24: =SUMIF(tbl_sales[Product line],"Home and lifestyle",tbl_sales[Sales]) -> 53861.913
A25: 636-48-8204 | B25: Alex | C25: Yangon | D25: Member | E25: Female | F25: Electronic accessories | G25: 34.56 | H25: 5 | I25: 8.64 | J25: 181.44 | K25: 43513 | L25: 0.46875 | M25: Ewallet | N25: 172.8 | O25: 4.7619048 | P25: 8.64 | Q25: 9.9 | R25: =TEXT(K25,"mmmm") -> February | S25: =MONTH(K25) -> 2 | T25: =IF(tbl_sales[[#This Row],[Sales]]>=500,"High Value","Standard") -> Standard | U25: =IF(tbl_sales[[#This Row],[Order Size]]="High Value","High Value Order","Standard Order") -> Standard Order | W25: Health and beauty | X25: =SUMIF(tbl_sales[Product line],"Health and beauty",tbl_sales[Sales]) -> 49193.739
A26: 549-59-1358 | B26: Alex | C26: Yangon | D26: Member | E26: Female | F26: Sports and travel | G26: 88.63 | H26: 3 | I26: 13.2945 | J26: 279.1845 | K26: 43526 | L26: 0.73333333 | M26: Ewallet | N26: 265.89 | O26: 4.7619048 | P26: 13.2945 | Q26: 6 | R26: =TEXT(K26,"mmmm") -> March | S26: =MONTH(K26) -> 3 | T26: =IF(tbl_sales[[#This Row],[Sales]]>=500,"High Value","Standard") -> Standard | U26: =IF(tbl_sales[[#This Row],[Order Size]]="High Value","High Value Order","Standard Order") -> Standard Order | W26: Food and beverages | X26: =SUMIF(tbl_sales[Product line],"Food and beverages",tbl_sales[Sales]) -> 56144.844
A27: 227-03-5010 | B27: Alex | C27: Yangon | D27: Member | E27: Female | F27: Home and lifestyle | G27: 52.59 | H27: 8 | I27: 21.036 | J27: 441.756 | K27: 43546 | L27: 0.80555556 | M27: Credit card | N27: 420.72 | O27: 4.7619048 | P27: 21.036 | Q27: 8.5 | R27: =TEXT(K27,"mmmm") -> March | S27: =MONTH(K27) -> 3 | T27: =IF(tbl_sales[[#This Row],[Sales]]>=500,"High Value","Standard") -> Standard | U27: =IF(tbl_sales[[#This Row],[Order Size]]="High Value","High Value Order","Standard Order") -> Standard Order | W27: Fashion accessories | X27: =SUMIF(tbl_sales[Product line],"Fashion accessories",tbl_sales[Sales]) -> 54305.895
A28: 649-29-6775 | B28: Cairo | C28: Mandalay | D28: Member | E28: Female | F28: Fashion accessories | G28: 33.52 | H28: 1 | I28: 1.676 | J28: 35.196 | K28: 43504 | L28: 0.64652778 | M28: Cash | N28: 33.52 | O28: 4.7619048 | P28: 1.676 | Q28: 6.7 | R28: =TEXT(K28,"mmmm") -> February | S28: =MONTH(K28) -> 2 | T28: =IF(tbl_sales[[#This Row],[Sales]]>=500,"High Value","Standard") -> Standard | U28: =IF(tbl_sales[[#This Row],[Order Size]]="High Value","High Value Order","Standard Order") -> Standard Order | W28: Sports and travel | X28: =SUMIF(tbl_sales[Product line],"Sports and travel",tbl_sales[Sales]) -> 55122.826
A29: 189-17-4241 | B29: Alex | C29: Yangon | D29: Member | E29: Female | F29: Fashion accessories | G29: 87.67 | H29: 2 | I29: 8.767 | J29: 184.107 | K29: 43534 | L29: 0.51180556 | M29: Credit card | N29: 175.34 | O29: 4.7619048 | P29: 8.767 | Q29: 7.7 | R29: =TEXT(K29,"mmmm") -> March | S29: =MONTH(K29) -> 3 | T29: =IF(tbl_sales[[#This Row],[Sales]]>=500,"High Value","Standard") -> Standard | U29: =IF(tbl_sales[[#This Row],[Order Size]]="High Value","High Value Order","Standard Order") -> Standard Order
A30: 145-94-9061 | B30: Cairo | C30: Mandalay | D30: Member | E30: Female | F30: Food and beverages | G30: 88.36 | H30: 5 | I30: 22.09 | J30: 463.89 | K30: 43490 | L30: 0.825 | M30: Cash | N30: 441.8 | O30: 4.7619048 | P30: 22.09 | Q30: 9.6 | R30: =TEXT(K30,"mmmm") -> January | S30: =MONTH(K30) -> 1 | T30: =IF(tbl_sales[[#This Row],[Sales]]>=500,"High Value","Standard") -> Standard | U30: =IF(tbl_sales[[#This Row],[Order Size]]="High Value","High Value Order","Standard Order") -> Standard Order | W30: Metric | X30: Value
A31: 848-62-7243 | B31: Alex | C31: Yangon | D31: Member | E31: Female | F31: Health and beauty | G31: 24.89 | H31: 9 | I31: 11.2005 | J31: 235.2105 | K31: 43539 | L31: 0.65 | M31: Cash | N31: 224.01 | O31: 4.7619048 | P31: 11.2005 | Q31: 7.4 | R31: =TEXT(K31,"mmmm") -> March | S31: =MONTH(K31) -> 3 | T31: =IF(tbl_sales[[#This Row],[Sales]]>=500,"High Value","Standard") -> Standard | U31: =IF(tbl_sales[[#This Row],[Order Size]]="High Value","High Value Order","Standard Order") -> Standard Order | W31: Total Profit | X31: =SUM(tbl_sales[gross income]) -> 15379.369
A32: 871-79-8483 | B32: Cairo | C32: Mandalay | D32: Member | E32: Female | F32: Fashion accessories | G32: 94.13 | H32: 5 | I32: 23.5325 | J32: 494.1825 | K32: 43521 | L32: 0.81875 | M32: Credit card | N32: 470.65 | O32: 4.7619048 | P32: 23.5325 | Q32: 4.8 | R32: =TEXT(K32,"mmmm") -> February | S32: =MONTH(K32) -> 2 | T32: =IF(tbl_sales[[#This Row],[Sales]]>=500,"High Value","Standard") -> Standard | U32: =IF(tbl_sales[[#This Row],[Order Size]]="High Value","High Value Order","Standard Order") -> Standard Order | W32: Profit % | X32: =SUM(tbl_sales[gross income])/SUM(tbl_sales[Sales]) -> 0.047619048
A33: 149-71-6266 | B33: Cairo | C33: Mandalay | D33: Member | E33: Female | F33: Sports and travel | G33: 78.07 | H33: 9 | I33: 35.1315 | J33: 737.7615 | K33: 43493 | L33: 0.52986111 | M33: Cash | N33: 702.63 | O33: 4.7619048 | P33: 35.1315 | Q33: 4.5 | R33: =TEXT(K33,"mmmm") -> January | S33: =MONTH(K33) -> 1 | T33: =IF(tbl_sales[[#This Row],[Sales]]>=500,"High Value","Standard") -> High Value | U33: =IF(tbl_sales[[#This Row],[Order Size]]="High Value","High Value Order","Standard Order") -> High Value Order
A34: 640-49-2076 | B34: Cairo | C34: Mandalay | D34: Member | E34: Female | F34: Sports and travel | G34: 83.78 | H34: 8 | I34: 33.512 | J34: 703.752 | K34: 43475 | L34: 0.61736111 | M34: Cash | N34: 670.24 | O34: 4.7619048 | P34: 33.512 | Q34: 5.1 | R34: =TEXT(K34,"mmmm") -> January | S34: =MONTH(K34) -> 1 | T34: =IF(tbl_sales[[#This Row],[Sales]]>=500,"High Value","Standard") -> High Value | U34: =IF(tbl_sales[[#This Row],[Order Size]]="High Value","High Value Order","Standard Order") -> High Value Order | W34: Branch | X34: Order Size | Y34: Number of Orders
A35: 595-11-5460 | B35: Alex | C35: Yangon | D35: Member | E35: Female | F35: Health and beauty | G35: 96.58 | H35: 2 | I35: 9.658 | J35: 202.818 | K35: 43539 | L35: 0.425 | M35: Credit card | N35: 193.16 | O35: 4.7619048 | P35: 9.658 | Q35: 5.1 | R35: =TEXT(K35,"mmmm") -> March | S35: =MONTH(K35) -> 3 | T35: =IF(tbl_sales[[#This Row],[Sales]]>=500,"High Value","Standard") -> Standard | U35: =IF(tbl_sales[[#This Row],[Order Size]]="High Value","High Value Order","Standard Order") -> Standard Order | W35: Alex | X35: Standard | Y35: =COUNTIFS(tbl_sales[Branch],"Alex",tbl_sales[Order Size],"Standard") -> 269
A36: 183-56-6882 | B36: Giza | C36: Naypyitaw | D36: Member | E36: Female | F36: Food and beverages | G36: 99.42 | H36: 4 | I36: 19.884 | J36: 417.564 | K36: 43502 | L36: 0.44583333 | M36: Ewallet | N36: 397.68 | O36: 4.7619048 | P36: 19.884 | Q36: 7.5 | R36: =TEXT(K36,"mmmm") -> February | S36: =MONTH(K36) -> 2 | T36: =IF(tbl_sales[[#This Row],[Sales]]>=500,"High Value","Standard") -> Standard | U36: =IF(tbl_sales[[#This Row],[Order Size]]="High Value","High Value Order","Standard Order") -> Standard Order | W36: Alex | X36: High Value | Y36: =COUNTIFS(tbl_sales[Branch],"Alex",tbl_sales[Order Size],"High Value") -> 71
A37: 232-16-2483 | B37: Giza | C37: Naypyitaw | D37: Member | E37: Female | F37: Sports and travel | G37: 68.12 | H37: 1 | I37: 3.406 | J37: 71.526 | K37: 43472 | L37: 0.51944444 | M37: Ewallet | N37: 68.12 | O37: 4.7619048 | P37: 3.406 | Q37: 6.8 | R37: =TEXT(K37,"mmmm") -> January | S37: =MONTH(K37) -> 1 | T37: =IF(tbl_sales[[#This Row],[Sales]]>=500,"High Value","Standard") -> Standard | U37: =IF(tbl_sales[[#This Row],[Order Size]]="High Value","High Value Order","Standard Order") -> Standard Order | W37: Cairo | X37: Standard | Y37: =COUNTIFS(tbl_sales[Branch],"Cairo",tbl_sales[Order Size],"Standard") -> 256
A38: 129-29-8530 | B38: Alex | C38: Yangon | D38: Member | E38: Female | F38: Sports and travel | G38: 62.62 | H38: 5 | I38: 15.655 | J38: 328.755 | K38: 43534 | L38: 0.80208333 | M38: Ewallet | N38: 313.1 | O38: 4.7619048 | P38: 15.655 | Q38: 7 | R38: =TEXT(K38,"mmmm") -> March | S38: =MONTH(K38) -> 3 | T38: =IF(tbl_sales[[#This Row],[Sales]]>=500,"High Value","Standard") -> Standard | U38: =IF(tbl_sales[[#This Row],[Order Size]]="High Value","High Value Order","Standard Order") -> Standard Order | W38: Cairo | X38: High Value | Y38: =COUNTIFS(tbl_sales[Branch],"Cairo",tbl_sales[Order Size],"High Value") -> 76
A39: 272-65-1806 | B39: Alex | C39: Yangon | D39: Member | E39: Female | F39: Electronic accessories | G39: 60.88 | H39: 9 | I39: 27.396 | J39: 575.316 | K39: 43480 | L39: 0.72013889 | M39: Ewallet | N39: 547.92 | O39: 4.7619048 | P39: 27.396 | Q39: 4.7 | R39: =TEXT(K39,"mmmm") -> January | S39: =MONTH(K39) -> 1 | T39: =IF(tbl_sales[[#This Row],[Sales]]>=500,"High Value","Standard") -> High Value | U39: =IF(tbl_sales[[#This Row],[Order Size]]="High Value","High Value Order","Standard Order") -> High Value Order | W39: Giza | X39: Standard | Y39: =COUNTIFS(tbl_sales[Branch],"Giza",tbl_sales[Order Size],"Standard") -> 248
A40: 333-73-7901 | B40: Giza | C40: Naypyitaw | D40: Member | E40: Female | F40: Health and beauty | G40: 54.92 | H40: 8 | I40: 21.968 | J40: 461.328 | K40: 43547 | L40: 0.55833333 | M40: Ewallet | N40: 439.36 | O40: 4.7619048 | P40: 21.968 | Q40: 7.6 | R40: =TEXT(K40,"mmmm") -> March | S40: =MONTH(K40) -> 3 | T40: =IF(tbl_sales[[#This Row],[Sales]]>=500,"High Value","Standard") -> Standard | U40: =IF(tbl_sales[[#This Row],[Order Size]]="High Value","High Value Order","Standard Order") -> Standard Order | W40: Giza | X40: High Value | Y40: =COUNTIFS(tbl_sales[Branch],"Giza",tbl_sales[Order Size],"High Value") -> 80
A41: 777-82-7220 | B41: Cairo | C41: Mandalay | D41: Member | E41: Female | F41: Home and lifestyle | G41: 30.12 | H41: 8 | I41: 12.048 | J41: 253.008 | K41: 43527 | L41: 0.54236111 | M41: Cash | N41: 240.96 | O41: 4.7619048 | P41: 12.048 | Q41: 7.7 | R41: =TEXT(K41,"mmmm") -> March | S41: =MONTH(K41) -> 3 | T41: =IF(tbl_sales[[#This Row],[Sales]]>=500,"High Value","Standard") -> Standard | U41: =IF(tbl_sales[[#This Row],[Order Size]]="High Value","High Value Order","Standard Order") -> Standard Order
A42: 280-35-5823 | B42: Cairo | C42: Mandalay | D42: Member | E42: Female | F42: Home and lifestyle | G42: 86.72 | H42: 1 | I42: 4.336 | J42: 91.056 | K42: 43482 | L42: 0.78125 | M42: Ewallet | N42: 86.72 | O42: 4.7619048 | P42: 4.336 | Q42: 7.9 | R42: =TEXT(K42,"mmmm") -> January | S42: =MONTH(K42) -> 1 | T42: =IF(tbl_sales[[#This Row],[Sales]]>=500,"High Value","Standard") -> Standard | U42: =IF(tbl_sales[[#This Row],[Order Size]]="High Value","High Value Order","Standard Order") -> Standard Order | W42: Branch | X42: Month | Y42: Total Sales
A43: 554-53-8700 | B43: Giza | C43: Naypyitaw | D43: Member | E43: Female | F43: Home and lifestyle | G43: 56.11 | H43: 2 | I43: 5.611 | J43: 117.831 | K43: 43498 | L43: 0.42430556 | M43: Cash | N43: 112.22 | O43: 4.7619048 | P43: 5.611 | Q43: 6.3 | R43: =TEXT(K43,"mmmm") -> February | S43: =MONTH(K43) -> 2 | T43: =IF(tbl_sales[[#This Row],[Sales]]>=500,"High Value","Standard") -> Standard | U43: =IF(tbl_sales[[#This Row],[Order Size]]="High Value","High Value Order","Standard Order") -> Standard Order | W43: Alex | X43: January | Y43: =SUMIFS(tbl_sales[Sales],tbl_sales[Branch],"Alex",tbl_sales[Month],"January") -> 38681.128
A44: 354-25-5821 | B44: Cairo | C44: Mandalay | D44: Member | E44: Female | F44: Sports and travel | G44: 69.12 | H44: 6 | I44: 20.736 | J44: 435.456 | K44: 43504 | L44: 0.54375 | M44: Cash | N44: 414.72 | O44: 4.7619048 | P44: 20.736 | Q44: 5.6 | R44: =TEXT(K44,"mmmm") -> February | S44: =MONTH(K44) -> 2 | T44: =IF(tbl_sales[[#This Row],[Sales]]>=500,"High Value","Standard") -> Standard | U44: =IF(tbl_sales[[#This Row],[Order Size]]="High Value","High Value Order","Standard Order") -> Standard Order | W44: Alex | X44: February | Y44: =SUMIFS(tbl_sales[Sales],tbl_sales[Branch],"Alex",tbl_sales[Month],"February") -> 29860.121
A45: 228-96-1411 | B45: Giza | C45: Naypyitaw | D45: Member | E45: Female | F45: Food and beverages | G45: 98.7 | H45: 8 | I45: 39.48 | J45: 829.08 | K45: 43528 | L45: 0.86041667 | M45: Cash | N45: 789.6 | O45: 4.7619048 | P45: 39.48 | Q45: 7.6 | R45: =TEXT(K45,"mmmm") -> March | S45: =MONTH(K45) -> 3 | T45: =IF(tbl_sales[[#This Row],[Sales]]>=500,"High Value","Standard") -> High Value | U45: =IF(tbl_sales[[#This Row],[Order Size]]="High Value","High Value Order","Standard Order") -> High Value Order | W45: Alex | X45: March | Y45: =SUMIFS(tbl_sales[Sales],tbl_sales[Branch],"Alex",tbl_sales[Month],"March") -> 37659.122
A46: 617-15-4209 | B46: Giza | C46: Naypyitaw | D46: Member | E46: Female | F46: Health and beauty | G46: 15.37 | H46: 2 | I46: 1.537 | J46: 32.277 | K46: 43540 | L46: 0.82430556 | M46: Cash | N46: 30.74 | O46: 4.7619048 | P46: 1.537 | Q46: 7.2 | R46: =TEXT(K46,"mmmm") -> March | S46: =MONTH(K46) -> 3 | T46: =IF(tbl_sales[[#This Row],[Sales]]>=500,"High Value","Standard") -> Standard | U46: =IF(tbl_sales[[#This Row],[Order Size]]="High Value","High Value Order","Standard Order") -> Standard Order | W46: Cairo | X46: January | Y46: =SUMIFS(tbl_sales[Sales],tbl_sales[Branch],"Cairo",tbl_sales[Month],"January") -> 37176.059
A47: 132-32-9879 | B47: Cairo | C47: Mandalay | D47: Member | E47: Female | F47: Electronic accessories | G47: 93.96 | H47: 4 | I47: 18.792 | J47: 394.632 | K47: 43533 | L47: 0.75 | M47: Cash | N47: 375.84 | O47: 4.7619048 | P47: 18.792 | Q47: 9.5 | R47: =TEXT(K47,"mmmm") -> March | S47: =MONTH(K47) -> 3 | T47: =IF(tbl_sales[[#This Row],[Sales]]>=500,"High Value","Standard") -> Standard | U47: =IF(tbl_sales[[#This Row],[Order Size]]="High Value","High Value Order","Standard Order") -> Standard Order | W47: Cairo | X47: February | Y47: =SUMIFS(tbl_sales[Sales],tbl_sales[Branch],"Cairo",tbl_sales[Month],"February") -> 34424.271
A48: 370-41-7321 | B48: Cairo | C48: Mandalay | D48: Member | E48: Female | F48: Health and beauty | G48: 56.69 | H48: 9 | I48: 25.5105 | J48: 535.7205 | K48: 43523 | L48: 0.725 | M48: Credit card | N48: 510.21 | O48: 4.7619048 | P48: 25.5105 | Q48: 8.4 | R48: =TEXT(K48,"mmmm") -> February | S48: =MONTH(K48) -> 2 | T48: =IF(tbl_sales[[#This Row],[Sales]]>=500,"High Value","Standard") -> High Value | U48: =IF(tbl_sales[[#This Row],[Order Size]]="High Value","High Value Order","Standard Order") -> High Value Order | W48: Cairo | X48: March | Y48: =SUMIFS(tbl_sales[Sales],tbl_sales[Branch],"Cairo",tbl_sales[Month],"March") -> 34597.342
A49: 727-46-3608 | B49: Cairo | C49: Mandalay | D49: Member | E49: Female | F49: Food and beverages | G49: 20.01 | H49: 9 | I49: 9.0045 | J49: 189.0945 | K49: 43502 | L49: 0.65763889 | M49: Ewallet | N49: 180.09 | O49: 4.7619048 | P49: 9.0045 | Q49: 4.1 | R49: =TEXT(K49,"mmmm") -> February | S49: =MONTH(K49) -> 2 | T49: =IF(tbl_sales[[#This Row],[Sales]]>=500,"High Value","Standard") -> Standard | U49: =IF(tbl_sales[[#This Row],[Order Size]]="High Value","High Value Order","Standard Order") -> Standard Order | W49: Giza | X49: January | Y49: =SUMIFS(tbl_sales[Sales],tbl_sales[Branch],"Giza",tbl_sales[Month],"January") -> 40434.681
A50: 669-54-1719 | B50: Cairo | C50: Mandalay | D50: Member | E50: Female | F50: Electronic accessories | G50: 18.93 | H50: 6 | I50: 5.679 | J50: 119.259 | K50: 43506 | L50: 0.53125 | M50: Credit card | N50: 113.58 | O50: 4.7619048 | P50: 5.679 | Q50: 8.1 | R50: =TEXT(K50,"mmmm") -> February | S50: =MONTH(K50) -> 2 | T50: =IF(tbl_sales[[#This Row],[Sales]]>=500,"High Value","Standard") -> Standard | U50: =IF(tbl_sales[[#This Row],[Order Size]]="High Value","High Value Order","Standard Order") -> Standard Order | W50: Giza | X50: February | Y50: =SUMIFS(tbl_sales[Sales],tbl_sales[Branch],"Giza",tbl_sales[Month],"February") -> 32934.983
A51: 574-22-5561 | B51: Giza | C51: Naypyitaw | D51: Member | E51: Female | F51: Fashion accessories | G51: 82.63 | H51: 10 | I51: 41.315 | J51: 867.615 | K51: 43543 | L51: 0.71388889 | M51: Ewallet | N51: 826.3 | O51: 4.7619048 | P51: 41.315 | Q51: 7.9 | R51: =TEXT(K51,"mmmm") -> March | S51: =MONTH(K51) -> 3 | T51: =IF(tbl_sales[[#This Row],[Sales]]>=500,"High Value","Standard") -> High Value | U51: =IF(tbl_sales[[#This Row],[Order Size]]="High Value","High Value Order","Standard Order") -> High Value Order | W51: Giza | X51: March | Y51: =SUMIFS(tbl_sales[Sales],tbl_sales[Branch],"Giza",tbl_sales[Month],"March") -> 37199.043
A52: 326-78-5178 | B52: Giza | C52: Naypyitaw | D52: Member | E52: Female | F52: Food and beverages | G52: 91.4 | H52: 7 | I52: 31.99 | J52: 671.79 | K52: 43499 | L52: 0.42986111 | M52: Cash | N52: 639.8 | O52: 4.7619048 | P52: 31.99 | Q52: 9.5 | R52: =TEXT(K52,"mmmm") -> February | S52: =MONTH(K52) -> 2 | T52: =IF(tbl_sales[[#This Row],[Sales]]>=500,"High Value","Standard") -> High Value | U52: =IF(tbl_sales[[#This Row],[Order Size]]="High Value","High Value Order","Standard Order") -> High Value Order
A53: 162-48-8011 | B53: Alex | C53: Yangon | D53: Member | E53: Female | F53: Food and beverages | G53: 44.59 | H53: 5 | I53: 11.1475 | J53: 234.0975 | K53: 43506 | L53: 0.63194444 | M53: Cash | N53: 222.95 | O53: 4.7619048 | P53: 11.1475 | Q53: 8.5 | R53: =TEXT(K53,"mmmm") -> February | S53: =MONTH(K53) -> 2 | T53: =IF(tbl_sales[[#This Row],[Sales]]>=500,"High Value","Standard") -> Standard | U53: =IF(tbl_sales[[#This Row],[Order Size]]="High Value","High Value Order","Standard Order") -> Standard Order | W53: Branch | X53: Average Rating
A54: 616-24-2851 | B54: Cairo | C54: Mandalay | D54: Member | E54: Female | F54: Fashion accessories | G54: 17.87 | H54: 4 | I54: 3.574 | J54: 75.054 | K54: 43546 | L54: 0.6125 | M54: Ewallet | N54: 71.48 | O54: 4.7619048 | P54: 3.574 | Q54: 6.5 | R54: =TEXT(K54,"mmmm") -> March | S54: =MONTH(K54) -> 3 | T54: =IF(tbl_sales[[#This Row],[Sales]]>=500,"High Value","Standard") -> Standard | U54: =IF(tbl_sales[[#This Row],[Order Size]]="High Value","High Value Order","Standard Order") -> Standard Order | W54: Alex | X54: =AVERAGEIFS(tbl_sales[Rating],tbl_sales[Branch],"Alex") -> 7.0270588
A55: 778-71-5554 | B55: Giza | C55: Naypyitaw | D55: Member | E55: Female | F55: Fashion accessories | G55: 15.43 | H55: 1 | I55: 0.7715 | J55: 16.2015 | K55: 43490 | L55: 0.65694444 | M55: Credit card | N55: 15.43 | O55: 4.7619048 | P55: 0.7715 | Q55: 6.1 | R55: =TEXT(K55,"mmmm") -> January | S55: =MONTH(K55) -> 1 | T55: =IF(tbl_sales[[#This Row],[Sales]]>=500,"High Value","Standard") -> Standard | U55: =IF(tbl_sales[[#This Row],[Order Size]]="High Value","High Value Order","Standard Order") -> Standard Order | W55: Cairo | X55: =AVERAGEIFS(tbl_sales[Rating],tbl_sales[Branch],"Cairo") -> 6.8180723
A56: 242-55-6721 | B56: Cairo | C56: Mandalay | D56: Member | E56: Female | F56: Home and lifestyle | G56: 16.16 | H56: 2 | I56: 1.616 | J56: 33.936 | K56: 43531 | L56: 0.49236111 | M56: Ewallet | N56: 32.32 | O56: 4.7619048 | P56: 1.616 | Q56: 6.5 | R56: =TEXT(K56,"mmmm") -> March | S56: =MONTH(K56) -> 3 | T56: =IF(tbl_sales[[#This Row],[Sales]]>=500,"High Value","Standard") -> Standard | U56: =IF(tbl_sales[[#This Row],[Order Size]]="High Value","High Value Order","Standard Order") -> Standard Order | W56: Giza | X56: =AVERAGEIFS(tbl_sales[Rating],tbl_sales[Branch],"Giza") -> 7.0728659
A57: 399-46-5918 | B57: Giza | C57: Naypyitaw | D57: Member | E57: Female | F57: Electronic accessories | G57: 85.98 | H57: 8 | I57: 34.392 | J57: 722.232 | K57: 43524 | L57: 0.79236111 | M57: Cash | N57: 687.84 | O57: 4.7619048 | P57: 34.392 | Q57: 8.2 | R57: =TEXT(K57,"mmmm") -> February | S57: =MONTH(K57) -> 2 | T57: =IF(tbl_sales[[#This Row],[Sales]]>=500,"High Value","Standard") -> High Value | U57: =IF(tbl_sales[[#This Row],[Order Size]]="High Value","High Value Order","Standard Order") -> High Value Order
A58: 106-35-6779 | B58: Alex | C58: Yangon | D58: Member | E58: Female | F58: Home and lifestyle | G58: 44.34 | H58: 2 | I58: 4.434 | J58: 93.114 | K58: 43551 | L58: 0.47638889 | M58: Cash | N58: 88.68 | O58: 4.7619048 | P58: 4.434 | Q58: 5.8 | R58: =TEXT(K58,"mmmm") -> March | S58: =MONTH(K58) -> 3 | T58: =IF(tbl_sales[[#This Row],[Sales]]>=500,"High Value","Standard") -> Standard | U58: =IF(tbl_sales[[#This Row],[Order Size]]="High Value","High Value Order","Standard Order") -> Standard Order | W58: Branch | X58: Total Sales
A59: 635-40-6220 | B59: Alex | C59: Yangon | D59: Member | E59: Female | F59: Health and beauty | G59: 89.6 | H59: 8 | I59: 35.84 | J59: 752.64 | K59: 43503 | L59: 0.47777778 | M59: Ewallet | N59: 716.8 | O59: 4.7619048 | P59: 35.84 | Q59: 6.6 | R59: =TEXT(K59,"mmmm") -> February | S59: =MONTH(K59) -> 2 | T59: =IF(tbl_sales[[#This Row],[Sales]]>=500,"High Value","Standard") -> High Value | U59: =IF(tbl_sales[[#This Row],[Order Size]]="High Value","High Value Order","Standard Order") -> High Value Order | W59: Alex | X59: =_xlfn.XLOOKUP("Alex",W9:W11,X9:X11) -> 106200.37
A60: 817-48-8732 | B60: Alex | C60: Yangon | D60: Member | E60: Female | F60: Home and lifestyle | G60: 72.35 | H60: 10 | I60: 36.175 | J60: 759.675 | K60: 43485 | L60: 0.66319444 | M60: Cash | N60: 723.5 | O60: 4.7619048 | P60: 36.175 | Q60: 5.4 | R60: =TEXT(K60,"mmmm") -> January | S60: =MONTH(K60) -> 1 | T60: =IF(tbl_sales[[#This Row],[Sales]]>=500,"High Value","Standard") -> High Value | U60: =IF(tbl_sales[[#This Row],[Order Size]]="High Value","High Value Order","Standard Order") -> High Value Order | W60: Cairo | X60: =_xlfn.XLOOKUP("Cairo",W9:W11,X9:X11) -> 106197.67
A61: 120-06-4233 | B61: Giza | C61: Naypyitaw | D61: Member | E61: Female | F61: Electronic accessories | G61: 30.61 | H61: 6 | I61: 9.183 | J61: 192.843 | K61: 43536 | L61: 0.85833333 | M61: Cash | N61: 183.66 | O61: 4.7619048 | P61: 9.183 | Q61: 9.3 | R61: =TEXT(K61,"mmmm") -> March | S61: =MONTH(K61) -> 3 | T61: =IF(tbl_sales[[#This Row],[Sales]]>=500,"High Value","Standard") -> Standard | U61: =IF(tbl_sales[[#This Row],[Order Size]]="High Value","High Value Order","Standard Order") -> Standard Order | W61: Giza | X61: =_xlfn.XLOOKUP("Giza",W9:W11,X9:X11) -> 110568.71
A62: 285-68-5083 | B62: Giza | C62: Naypyitaw | D62: Member | E62: Female | F62: Sports and travel | G62: 24.74 | H62: 3 | I62: 3.711 | J62: 77.931 | K62: 43511 | L62: 0.74097222 | M62: Credit card | N62: 74.22 | O62: 4.7619048 | P62: 3.711 | Q62: 10 | R62: =TEXT(K62,"mmmm") -> February | S62: =MONTH(K62) -> 2 | T62: =IF(tbl_sales[[#This Row],[Sales]]>=500,"High Value","Standard") -> Standard | U62: =IF(tbl_sales[[#This Row],[Order Size]]="High Value","High Value Order","Standard Order") -> Standard Order
A63: 803-83-5989 | B63: Giza | C63: Naypyitaw | D63: Member | E63: Female | F63: Home and lifestyle | G63: 55.73 | H63: 6 | I63: 16.719 | J63: 351.099 | K63: 43520 | L63: 0.45486111 | M63: Ewallet | N63: 334.38 | O63: 4.7619048 | P63: 16.719 | Q63: 7 | R63: =TEXT(K63,"mmmm") -> February | S63: =MONTH(K63) -> 2 | T63: =IF(tbl_sales[[#This Row],[Sales]]>=500,"High Value","Standard") -> Standard | U63: =IF(tbl_sales[[#This Row],[Order Size]]="High Value","High Value Order","Standard Order") -> Standard Order
A64: 347-34-2234 | B64: Cairo | C64: Mandalay | D64: Member | E64: Female | F64: Sports and travel | G64: 55.07 | H64: 9 | I64: 24.7815 | J64: 520.4115 | K64: 43499 | L64: 0.56944444 | M64: Ewallet | N64: 495.63 | O64: 4.7619048 | P64: 24.7815 | Q64: 10 | R64: =TEXT(K64,"mmmm") -> February | S64: =MONTH(K64) -> 2 | T64: =IF(tbl_sales[[#This Row],[Sales]]>=500,"High Value","Standard") -> High Value | U64: =IF(tbl_sales[[#This Row],[Order Size]]="High Value","High Value Order","Standard Order") -> High Value Order
A65: 199-75-8169 | B65: Alex | C65: Yangon | D65: Member | E65: Female | F65: Sports and travel | G65: 15.81 | H65: 10 | I65: 7.905 | J65: 166.005 | K65: 43530 | L65: 0.51875 | M65: Credit card | N65: 158.1 | O65: 4.7619048 | P65: 7.905 | Q65: 8.6 | R65: =TEXT(K65,"mmmm") -> March | S65: =MONTH(K65) -> 3 | T65: =IF(tbl_sales[[#This Row],[Sales]]>=500,"High Value","Standard") -> Standard | U65: =IF(tbl_sales[[#This Row],[Order Size]]="High Value","High Value Order","Standard Order") -> Standard Order
A66: 853-23-2453 | B66: Cairo | C66: Mandalay | D66: Member | E66: Female | F66: Health and beauty | G66: 75.74 | H66: 4 | I66: 15.148 | J66: 318.108 | K66: 43510 | L66: 0.60763889 | M66: Cash | N66: 302.96 | O66: 4.7619048 | P66: 15.148 | Q66: 7.6 | R66: =TEXT(K66,"mmmm") -> February | S66: =MONTH(K66) -> 2 | T66: =IF(tbl_sales[[#This Row],[Sales]]>=500,"High Value","Standard") -> Standard | U66: =IF(tbl_sales[[#This Row],[Order Size]]="High Value","High Value Order","Standard Order") -> Standard Order
A67: 877-22-3308 | B67: Alex | C67: Yangon | D67: Member | E67: Female | F67: Health and beauty | G67: 15.87 | H67: 10 | I67: 7.935 | J67: 166.635 | K67: 43537 | L67: 0.69444444 | M67: Cash | N67: 158.7 | O67: 4.7619048 | P67: 7.935 | Q67: 5.8 | R67: =TEXT(K67,"mmmm") -> March | S67: =MONTH(K67) -> 3 | T67: =IF(tbl_sales[[#This Row],[Sales]]>=500,"High Value","Standard") -> Standard | U67: =IF(tbl_sales[[#This Row],[Order Size]]="High Value","High Value Order","Standard Order") -> Standard Order
A68: 838-78-4295 | B68: Giza | C68: Naypyitaw | D68: Member | E68: Female | F68: Health and beauty | G68: 33.47 | H68: 2 | I68: 3.347 | J68: 70.287 | K68: 43506 | L68: 0.65486111 | M68: Ewallet | N68: 66.94 | O68: 4.7619048 | P68: 3.347 | Q68: 6.7 | R68: =TEXT(K68,"mmmm") -> February | S68: =MONTH(K68) -> 2 | T68: =IF(tbl_sales[[#This Row],[Sales]]>=500,"High Value","Standard") -> Standard | U68: =IF(tbl_sales[[#This Row],[Order Size]]="High Value","High Value Order","Standard Order") -> Standard Order
A69: 109-28-2512 | B69: Cairo | C69: Mandalay | D69: Member | E69: Female | F69: Fashion accessories | G69: 97.61 | H69: 6 | I69: 29.283 | J69: 614.943 | K69: 43472 | L69: 0.62569444 | M69: Ewallet | N69: 585.66 | O69: 4.7619048 | P69: 29.283 | Q69: 9.9 | R69: =TEXT(K69,"mmmm") -> January | S69: =MONTH(K69) -> 1 | T69: =IF(tbl_sales[[#This Row],[Sales]]>=500,"High Value","Standard") -> High Value | U69: =IF(tbl_sales[[#This Row],[Order Size]]="High Value","High Value Order","Standard Order") -> High Value Order
A70: 232-11-3025 | B70: Alex | C70: Yangon | D70: Member | E70: Female | F70: Sports and travel | G70: 78.77 | H70: 10 | I70: 39.385 | J70: 827.085 | K70: 43489 | L70: 0.41944444 | M70: Cash | N70: 787.7 | O70: 4.7619048 | P70: 39.385 | Q70: 6.4 | R70: =TEXT(K70,"mmmm") -> January | S70: =MONTH(K70) -> 1 | T70: =IF(tbl_sales[[#This Row],[Sales]]>=500,"High Value","Standard") -> High Value | U70: =IF(tbl_sales[[#This Row],[Order Size]]="High Value","High Value Order","Standard Order") -> High Value Order
A71: 382-03-4532 | B71: Alex | C71: Yangon | D71: Member | E71: Female | F71: Health and beauty | G71: 18.33 | H71: 1 | I71: 0.9165 | J71: 19.2465 | K71: 43498 | L71: 0.78472222 | M71: Cash | N71: 18.33 | O71: 4.7619048 | P71: 0.9165 | Q71: 4.3 | R71: =TEXT(K71,"mmmm") -> February | S71: =MONTH(K71) -> 2 | T71: =IF(tbl_sales[[#This Row],[Sales]]>=500,"High Value","Standard") -> Standard | U71: =IF(tbl_sales[[#This Row],[Order Size]]="High Value","High Value Order","Standard Order") -> Standard Order
A72: 393-65-2792 | B72: Giza | C72: Naypyitaw | D72: Member | E72: Female | F72: Food and beverages | G72: 89.48 | H72: 10 | I72: 44.74 | J72: 939.54 | K72: 43471 | L72: 0.53194444 | M72: Credit card | N72: 894.8 | O72: 4.7619048 | P72: 44.74 | Q72: 9.6 | R72: =TEXT(K72,"mmmm") -> January | S72: =MONTH(K72) -> 1 | T72: =IF(tbl_sales[[#This Row],[Sales]]>=500,"High Value","Standard") -> High Value | U72: =IF(tbl_sales[[#This Row],[Order Size]]="High Value","High Value Order","Standard Order") -> High Value Order
A73: 796-12-2025 | B73: Giza | C73: Naypyitaw | D73: Member | E73: Female | F73: Fashion accessories | G73: 62.12 | H73: 10 | I73: 31.06 | J73: 652.26 | K73: 43507 | L73: 0.67986111 | M73: Cash | N73: 621.2 | O73: 4.7619048 | P73: 31.06 | Q73: 5.9 | R73: =TEXT(K73,"mmmm") -> February | S73: =MONTH(K73) -> 2 | T73: =IF(tbl_sales[[#This Row],[Sales]]>=500,"High Value","Standard") -> High Value | U73: =IF(tbl_sales[[#This Row],[Order Size]]="High Value","High Value Order","Standard Order") -> High Value Order
... A1001: 849-09-3807 | B1001: Alex | C1001: Yangon | D1001: Member | E1001: Female | F1001: Fashion accessories | G1001: 88.34 | H1001: 7 | I1001: 30.919 | J1001: 649.299 | K1001: 43514 | L1001: 0.56111111 | M1001: Cash | N1001: 618.38 | O1001: 4.7619048 | P1001: 30.919 | Q1001: 6.6 | R1001: =TEXT(K1001,"mmmm") -> February | S1001: =MONTH(K1001) -> 2 | T1001: =IF(tbl_sales[[#This Row],[Sales]]>=500,"High Value","Standard") -> High Value | U1001: =IF(tbl_sales[[#This Row],[Order Size]]="High Value","High Value Order","Standard Order") -> High Value Order
S1002: =MONTH(K1002) -> 1 | T1002: =IF(tbl_sales[[#This Row],[Sales]]>=500,"High Value","Standard") -> Standard | U1002: =IF(tbl_sales[[#This Row],[Order Size]]="High Value","High Value Order","Standard Order") -> Standard Order

Sheet Pivot_Analysis
A1: MONTHLY SALES PERFORMANCE | D1: TOP 10 PRODUCTS BY SALES | G1: SALES BY PAYMENT METHOD
J2: Count of Invoice_ID
A3: Row Labels | B3: Sum of Sales | D3: Row Labels | E3: Sum of Sales | G3: Row Labels | H3: Transactions | J3: 94
A4: February | B4: 29860.12 | D4: Electronic accessories | E4: 5202.771 | G4: Cash | H4: 32
A5: Grand Total | B5: 29860.12 | D5: Fashion accessories | E5: 5173.6335 | G5: Credit card | H5: 28
D6: Food and beverages | E6: 7054.2255 | G6: Ewallet | H6: 34
D7: Health and beauty | E7: 2915.4825 | G7: Grand Total | H7: 94
D8: Home and lifestyle | E8: 4771.6305
D9: Sports and travel | E9: 4742.3775
A10: PRODUCT LINE PERFORMANCE | D10: Grand Total | E10: 29860.121
A12: Row Labels | B12: Sum of Sales | G12: KPI PIVOT_CHARTS
A13: Electronic accessories | B13: 5202.771 | D13: TOP 10 ORDERS BY SALES | G13: Count of Invoice_ID | H13: Sum of cogs | I13: Sum of Sales | J13: Sum of Quantity | K13: Count of Product line | L13: Sum of gross income | M13: Average of Rating
A14: Fashion accessories | B14: 5173.6335 | G14: 94 | H14: 28438.21 | I14: 29860.12 | J14: 493 | K14: 94 | L14: 1421.9105 | M14: 7.0074468
A15: Food and beverages | B15: 7054.2255 | D15: Row Labels | E15: Sum of Sales
A16: Health and beauty | B16: 2915.4825 | D16: 135-84-8019 | E16: 736.4385
A17: Home and lifestyle | B17: 4771.6305 | D17: 243-55-8457 | E17: 781.62
A18: Sports and travel | B18: 4742.3775 | D18: 384-59-6655 | E18: 932.337
A19: Grand Total | B19: 29860.121 | D19: 453-33-6436 | E19: 782.208
D20: 635-40-6220 | E20: 752.64
D21: 638-60-7125 | E21: 836.304
A22: BRANCH PERFORMANCE | D22: 687-47-8271 | E22: 1039.29
D23: 742-04-5161 | E23: 764.19
A24: Row Labels | B24: Sum of Sales | D24: 803-17-8013 | E24: 745.836
A25: Alex | B25: 29860.12 | D25: 827-77-7633 | E25: 926.9505
A26: Grand Total | B26: 29860.12 | D26: Grand Total | E26: 8297.814

Sheet Dashboard
A1: SUPERMARKET SALES ANALYTICS DASHBOARD
B2: TOTAL SALES | C2: TOTAL PROFIT | D2: TOTAL QUANTITY | E2: TOTAL COGS | F2: TOTAL GROSS INCOME | G2: AVERAGE RATING
B3: =GETPIVOTDATA("Sum of Sales",Pivot_Analysis!$G$13) -> 29860.12 | C3: =Dashboard!B3 -> 29860.12 | D3: =GETPIVOTDATA("Sum of Quantity",Pivot_Analysis!$G$13) -> 493 | E3: =GETPIVOTDATA("Sum of cogs",Pivot_Analysis!$G$13) -> 28438.21 | F3: =GETPIVOTDATA("Sum of gross income",Pivot_Analysis!$L$13) -> 1421.9105 | G3: =GETPIVOTDATA("Average of Rating",Pivot_Analysis!$L$13) -> 7.0074468
